prosper_api/__init__.py
prosper_api/auth_token_manager.py
prosper_api/client.py
prosper_api/models/__init__.py
prosper_api/models/enums.py
prosper_api-0.11.0.dist-info/LICENSE
prosper_api-0.11.0.dist-info/METADATA
prosper_api-0.11.0.dist-info/WHEEL
prosper_api-0.11.0.dist-info/RECORD
