Metadata-Version: 2.1
Name: prosper-api
Version: 0.11.0
Summary: Python trading library for Prosper.com
Home-page: https://github.com/grahamtt/prosper-api
License: Apache-2.0
Author: Graham Tibbitts
Author-email: graham.tibbitts@gmail.com
Requires-Python: >=3.9,<4.0
Classifier: License :: OSI Approved :: Apache Software License
Classifier: Operating System :: OS Independent
Classifier: Programming Language :: Python :: 3
Classifier: Programming Language :: Python :: 3.9
Classifier: Programming Language :: Python :: 3.10
Classifier: Programming Language :: Python :: 3.11
Classifier: Programming Language :: Python :: 3 :: Only
Classifier: Programming Language :: Python :: 3.12
Classifier: Programming Language :: Python :: 3.8
Classifier: Topic :: Office/Business :: Financial :: Investment
Provides-Extra: secure
Requires-Dist: backoff (>=2.2.1,<3.0.0)
Requires-Dist: dpath (>=2.1.6,<3.0.0)
Requires-Dist: keyring (>=24.2.0,<25.0.0) ; extra == "secure"
Requires-Dist: prosper-shared (>=0.8.1,<0.9.0)
Requires-Dist: pydantic (>=2.7.4,<3.0.0)
Requires-Dist: ratelimit (>=2.2.1,<3.0.0)
Requires-Dist: requests (>=2.31.0,<3.0.0)
Requires-Dist: schema (>=0.7.5,<0.8.0)
Requires-Dist: simplejson (>=3.19.2,<4.0.0)
Project-URL: Repository, https://github.com/grahamtt/prosper-api
